mailersend_backend/__init__.py
mailersend_backend/mail.py
django_mailersend_backend-0.1.1.dist-info/WHEEL
django_mailersend_backend-0.1.1.dist-info/METADATA
django_mailersend_backend-0.1.1.dist-info/RECORD
